<?xml version="1.0" encoding="UTF-8" ?>  
<!DOCTYPE mapper PUBLIC "-//mybatis.org//DTD Mapper 3.0//EN" 
"http://mybatis.org/dtd/mybatis-3-mapper.dtd">
<mapper namespace="com.asiainfo.label.dao.SysLabelDao">
	
	<resultMap type="com.asiainfo.entity.SysLabel" id="sysLabelMap">
		<id property="id" column="id"/>
		<result property="keyName" column="key_name"/>
		<result property="comment" column="comment"/>
		<result property="javaType" column="java_type"/>
		<result property="format" column="format"/>
	</resultMap>
	
	<select id="selectSysLabel" resultMap="sysLabelMap">
		select * from sys_label
	
	</select>
</mapper>